rsazure_openai_toolkit/__init__.py
rsazure_openai_toolkit/cli/__init__.py
rsazure_openai_toolkit/cli/cli.py
rsazure_openai_toolkit/cli/tools.py
rsazure_openai_toolkit/conversession/__init__.py
rsazure_openai_toolkit/conversession/conversession.py
rsazure_openai_toolkit/core/__init__.py
rsazure_openai_toolkit/core/integration.py
rsazure_openai_toolkit/env/__init__.py
rsazure_openai_toolkit/env/config.py
rsazure_openai_toolkit/logging/__init__.py
rsazure_openai_toolkit/logging/interaction_logger.py
rsazure_openai_toolkit/models/__init__.py
rsazure_openai_toolkit/models/context.py
rsazure_openai_toolkit/models/results.py
rsazure_openai_toolkit/prompts/__init__.py
rsazure_openai_toolkit/prompts/agent.py
rsazure_openai_toolkit/prompts/fallback_agent.py
rsazure_openai_toolkit/prompts/manager.py
rsazure_openai_toolkit/prompts/model.py
rsazure_openai_toolkit/samples/__init__.py
rsazure_openai_toolkit/samples/generator.py
rsazure_openai_toolkit/samples/templates/basic_usage.py.j2
rsazure_openai_toolkit/samples/templates/chat_loop_usage.py.j2
rsazure_openai_toolkit/samples/templates/env.example.py.j2
rsazure_openai_toolkit/samples/templates/env_chat_loop_usage.py.j2
rsazure_openai_toolkit/samples/templates/env_usage.py.j2
rsazure_openai_toolkit/session/__init__.py
rsazure_openai_toolkit/session/session.py
rsazure_openai_toolkit/utils/__init__.py
rsazure_openai_toolkit/utils/utils.py
rsazure_openai_toolkit-0.7.3.dist-info/licenses/LICENSE
rsazure_openai_toolkit-0.7.3.dist-info/METADATA
rsazure_openai_toolkit-0.7.3.dist-info/WHEEL
rsazure_openai_toolkit-0.7.3.dist-info/entry_points.txt
rsazure_openai_toolkit-0.7.3.dist-info/top_level.txt
rsazure_openai_toolkit-0.7.3.dist-info/RECORD
