Metadata-Version: 2.4
Name: rsazure-openai-toolkit
Version: 0.7.3
Summary: A fast, modular, secure, and auditable toolkit to integrate with Azure OpenAI — with a friendly CLI and dev-first architecture.
Author-email: Renan Siqueira Antonio <renan.siqu@gmail.com>
License: MIT
Project-URL: Homepage, https://github.com/renan-siqueira/rsazure-openai-toolkit
Project-URL: Repository, https://github.com/renan-siqueira/rsazure-openai-toolkit
Project-URL: Documentation, https://github.com/renan-siqueira/rsazure-openai-toolkit/tree/main/docs
Project-URL: Security Policy, https://github.com/renan-siqueira/rsazure-openai-toolkit/security/policy
Keywords: azure,openai,chatgpt,llm,cli,toolkit,prompt,chatbot,azure-openai,prompt-engineering,developer-tools
Classifier: Development Status :: 4 - Beta
Classifier: Intended Audience :: Developers
Classifier: License :: OSI Approved :: MIT License
Classifier: Programming Language :: Python :: 3
Classifier: Programming Language :: Python :: 3.9
Classifier: Programming Language :: Python :: 3.10
Classifier: Programming Language :: Python :: 3.11
Classifier: Topic :: Software Development :: Libraries
Classifier: Topic :: Utilities
Classifier: Topic :: Documentation
Requires-Python: >=3.9
License-File: LICENSE
Requires-Dist: openai>=1.0.0
Requires-Dist: tenacity>=8.2.0
Requires-Dist: python-dotenv>=1.0.0
Requires-Dist: click>=8.1.0
Requires-Dist: Jinja2>=3.1.2
Requires-Dist: tiktoken>=0.9.0
Requires-Dist: pyyaml>=0.6.0
Dynamic: license-file
